ambibulb/__init__.py
ambibulb/__main__.py
ambibulb/ambibulb_config.py
ambibulb/color_detect.py
ambibulb/image_compose.py
ambibulb/ir_light_bulb.py
ambibulb/snapshot_bcm.abi3.so
ambibulb-0.0.51.dist-info/LICENSE
ambibulb-0.0.51.dist-info/METADATA
ambibulb-0.0.51.dist-info/WHEEL
ambibulb-0.0.51.dist-info/entry_points.txt
ambibulb-0.0.51.dist-info/top_level.txt
ambibulb-0.0.51.dist-info/RECORD
