Metadata-Version: 2.1
Name: ambibulb
Version: 0.0.51
Summary: Python utility controls the color of RC lights based on the dominant color of an image on your screen.
Home-page: https://github.com/bespsm/ambibulb
Author: Sergey B
Author-email: dkc.sergey.88@hotmail.com
License: MIT
Platform: linux
Classifier: Development Status :: 4 - Beta
Classifier: Environment :: Console
Classifier: Intended Audience :: Developers
Classifier: License :: OSI Approved :: MIT License
Classifier: Operating System :: POSIX :: Linux
Classifier: Programming Language :: Python :: 3.7
Classifier: Programming Language :: Python :: Implementation :: CPython
Classifier: Programming Language :: Python :: Implementation :: PyPy
Classifier: Topic :: Utilities
Classifier: Topic :: Multimedia :: Graphics
Classifier: Topic :: Multimedia :: Graphics :: Capture :: Screen Capture
Requires-Python: >=3.7
Requires-Dist: Pillow (>=8.0.0)
Requires-Dist: cffi (>=1.13)
Requires-Dist: joblib (>=0.11)
Requires-Dist: numpy (>=1.3.13)
Requires-Dist: scikit-learn (>=0.23.2)
Requires-Dist: scipy (>=0.19.1)
Requires-Dist: systemd (>=0.16.1)
Requires-Dist: threadpoolctl (>=2.0.0)
Requires-Dist: whiptail-dialogs (>=0.3.2)
